{
  "loader": "bonsaitrees4:multiblockmodel",
  "version": 4,
  "ref": {
    "a": {"Properties":{"axis":"y"},"Name":"biomeswevegone:aspen_log"},
    "b": {"Properties":{"waterlogged":"false","persistent":"false","distance":"2"},"Name":"biomeswevegone:aspen_leaves"},
    "c": {"Properties":{"waterlogged":"false","persistent":"false","distance":"1"},"Name":"biomeswevegone:aspen_leaves"},
    "d": {"Properties":{"waterlogged":"false","persistent":"false","distance":"3"},"Name":"biomeswevegone:aspen_leaves"},
    "e": {"Properties":{"waterlogged":"false","facing":"east"},"Name":"biomeswevegone:shelf_fungi"},
    "f": {"Properties":{"waterlogged":"false","persistent":"false","distance":"4"},"Name":"biomeswevegone:aspen_leaves"},
    "g": {"Properties":{"waterlogged":"false","facing":"south"},"Name":"biomeswevegone:shelf_fungi"},
    "h": {"Properties":{"axis":"z"},"Name":"biomeswevegone:aspen_log"}
  },
  "shape": [
    [
      "       ",
      "       ",
      "       ",
      "       ",
      "fdbd   ",
      " db    ",
      "       ",
      "       ",
      "       ",
      "       ",
      "       ",
      "       ",
      "       ",
      "       ",
      "       ",
      "       "
    ],
    [
      "       ",
      "       ",
      " dbd   ",
      "  cb   ",
      " bc    ",
      "dbcb   ",
      "  b    ",
      "       ",
      "   e   ",
      "       ",
      "       ",
      "       ",
      "       ",
      "       ",
      "       ",
      "       "
    ],
    [
      "  d    ",
      "  b    ",
      " bcb   ",
      " cacb  ",
      "bcac   ",
      " cacbd ",
      "  ccb  ",
      "  ecb  ",
      "  bc   ",
      "       ",
      "   cb  ",
      "   c   ",
      "       ",
      "   a   ",
      "   a   ",
      "   a   "
    ],
    [
      "       ",
      "  d    ",
      "  b    ",
      "dbccb  ",
      "d cac  ",
      " bcacb ",
      "  cacbd",
      "  cacb ",
      "  cac  ",
      "  cahg ",
      "  cac  ",
      "   a   ",
      "   a   ",
      "   a   ",
      "  aaa  ",
      "  aaa  "
    ],
    [
      "       ",
      "       ",
      "       ",
      "   b   ",
      "  bcb  ",
      "   cbd ",
      "  bcbb ",
      "  bc   ",
      "   cb  ",
      "   c   ",
      "       ",
      "       ",
      "       ",
      "   a   ",
      "   a   ",
      "   a   "
    ],
    [
      "       ",
      "       ",
      "       ",
      "       ",
      "       ",
      "    df ",
      "   bb  ",
      "       ",
      "       ",
      "       ",
      "       ",
      "       ",
      "       ",
      "       ",
      "       ",
      "       "
    ]
  ]
}
