{
  "loader": "bonsaitrees4:multiblockmodel",
  "version": 4,
  "ref": {
    "a": {"Properties":{"waterlogged":"false","uncovered":"false","persistent":"false","distance":"3"},"Name":"occultism:otherworld_leaves_natural"},
    "b": {"Properties":{"waterlogged":"false","uncovered":"false","persistent":"false","distance":"1"},"Name":"occultism:otherworld_leaves_natural"},
    "c": {"Properties":{"waterlogged":"false","uncovered":"false","persistent":"false","distance":"4"},"Name":"occultism:otherworld_leaves_natural"},
    "d": {"Properties":{"waterlogged":"false","uncovered":"false","persistent":"false","distance":"2"},"Name":"occultism:otherworld_leaves_natural"},
    "e": {"Properties":{"uncovered":"false","axis":"y"},"Name":"occultism:otherworld_log_natural"},
    "f": {"Properties":{"waterlogged":"false","uncovered":"false","persistent":"false","distance":"5"},"Name":"occultism:otherworld_leaves_natural"}
  },
  "shape": [
    [
      "     ",
      "     ",
      " cacf",
      " cac ",
      "     "
    ],
    [
      "  d  ",
      " dbd ",
      "cadac",
      "aadac",
      "     "
    ],
    [
      " dbd ",
      " beb ",
      "adeda",
      "ddeda",
      "  e  "
    ],
    [
      "  d  ",
      " dbd ",
      "cadac",
      "addac",
      "     "
    ],
    [
      "     ",
      "     ",
      "ccacf",
      "fada ",
      "     "
    ]
  ]
}
